LICENSE
MANIFEST.in
README.rst
setup.cfg
setup.py
tw2/__init__.py
tw2.jqplugins.gritter.egg-info/PKG-INFO
tw2.jqplugins.gritter.egg-info/SOURCES.txt
tw2.jqplugins.gritter.egg-info/dependency_links.txt
tw2.jqplugins.gritter.egg-info/entry_points.txt
tw2.jqplugins.gritter.egg-info/namespace_packages.txt
tw2.jqplugins.gritter.egg-info/not-zip-safe
tw2.jqplugins.gritter.egg-info/requires.txt
tw2.jqplugins.gritter.egg-info/top_level.txt
tw2/jqplugins/__init__.py
tw2/jqplugins/gritter/__init__.py
tw2/jqplugins/gritter/base.py
tw2/jqplugins/gritter/static/jquery/gritter/README.markdown
tw2/jqplugins/gritter/static/jquery/gritter/index.html
tw2/jqplugins/gritter/static/jquery/gritter/css/jquery.gritter.css
tw2/jqplugins/gritter/static/jquery/gritter/images/gritter-long.png
tw2/jqplugins/gritter/static/jquery/gritter/images/gritter.png
tw2/jqplugins/gritter/static/jquery/gritter/images/ie-spacer.gif
tw2/jqplugins/gritter/static/jquery/gritter/images/trees.jpg
tw2/jqplugins/gritter/static/jquery/gritter/js/jquery.gritter.js
tw2/jqplugins/gritter/static/jquery/gritter/js/jquery.gritter.min.js